{"name": "S4-ADL1_Cleanup", "type": "Cleanup", "events": [{"type": "Cheese", "name": "Cheese_7", "start_time": 7, "end_time": 8}, {"type": "Fridge", "name": "Fridge_10", "start_time": 10, "end_time": 10}, {"type": "Fridge", "name": "Fridge_10", "start_time": 10, "end_time": 12}, {"type": "Fridge", "name": "Fridge_26", "start_time": 26, "end_time": 26}, {"type": "Fridge", "name": "Fridge_26", "start_time": 26, "end_time": 28}, {"type": "Knife", "name": "Knife_32", "start_time": 32, "end_time": 42}, {"type": "Plate", "name": "Plate_47", "start_time": 47, "end_time": 59}, {"type": "Plate", "name": "Plate_62", "start_time": 62, "end_time": 66}, {"type": "Dishwasher", "name": "Dishwasher_78", "start_time": 78, "end_time": 80}, {"type": "Dishwasher", "name": "Dishwasher_86", "start_time": 86, "end_time": 87}, {"type": "Dishwasher", "name": "Dishwasher_87", "start_time": 87, "end_time": 88}, {"type": "Cup", "name": "Cup_116", "start_time": 116, "end_time": 120}, {"type": "Fridge", "name": "Fridge_140", "start_time": 140, "end_time": 142}, {"type": "Fridge", "name": "Fridge_143", "start_time": 143, "end_time": 145}, {"type": "Drawer_lower", "name": "Drawer_lower_151", "start_time": 151, "end_time": 153}, {"type": "Drawer_lower", "name": "Drawer_lower_153", "start_time": 153, "end_time": 154}, {"type": "Knife", "name": "Knife_2", "start_time": 2, "end_time": 3}, {"type": "Cheese", "name": "Cheese_8", "start_time": 8, "end_time": 13}, {"type": "Salami", "name": "Salami_15", "start_time": 15, "end_time": 20}, {"type": "Bottle", "name": "Bottle_21", "start_time": 21, "end_time": 21}, {"type": "Bottle", "name": "Bottle_21", "start_time": 21, "end_time": 25}, {"type": "Knife", "name": "Knife_30", "start_time": 30, "end_time": 32}, {"type": "Dishwasher", "name": "Dishwasher_33", "start_time": 33, "end_time": 37}, {"type": "Dishwasher", "name": "Dishwasher_42", "start_time": 42, "end_time": 44}, {"type": "Dishwasher", "name": "Dishwasher_54", "start_time": 54, "end_time": 56}, {"type": "Plate", "name": "Plate_59", "start_time": 59, "end_time": 62}, {"type": "Dishwasher", "name": "Dishwasher_67", "start_time": 67, "end_time": 69}, {"type": "Glass", "name": "Glass_71", "start_time": 71, "end_time": 72}, {"type": "Glass", "name": "Glass_72", "start_time": 72, "end_time": 87}, {"type": "Cup", "name": "Cup_90", "start_time": 90, "end_time": 99}, {"type": "Cup", "name": "Cup_101", "start_time": 101, "end_time": 107}, {"type": "Dishwasher", "name": "Dishwasher_117", "start_time": 117, "end_time": 119}, {"type": "Cup", "name": "Cup_120", "start_time": 120, "end_time": 124}, {"type": "Dishwasher", "name": "Dishwasher_125", "start_time": 125, "end_time": 127}, {"type": "Spoon", "name": "Spoon_130", "start_time": 130, "end_time": 133}, {"type": "Dishwasher", "name": "Dishwasher_133", "start_time": 133, "end_time": 133}, {"type": "Dishwasher", "name": "Dishwasher_133", "start_time": 133, "end_time": 135}, {"type": "Bread", "name": "Bread_146", "start_time": 146, "end_time": 154}, {"type": "Drawer_top", "name": "Drawer_top_154", "start_time": 154, "end_time": 155}, {"type": "Drawer_top", "name": "Drawer_top_156", "start_time": 156, "end_time": 157}, {"type": "Table", "name": "Table_162", "start_time": 162, "end_time": 170}, {"type": "Table", "name": "Table_179", "start_time": 179, "end_time": 194}, {"type": "Table", "name": "Table_196", "start_time": 196, "end_time": 206}, {"type": "SWITCH_DISHWASHER_S1", "name": "SWITCH_DISHWASHER_S1_35", "start_time": 35, "end_time": 35}, {"type": "SWITCH_DISHWASHER_S1", "name": "SWITCH_DISHWASHER_S1_43", "start_time": 43, "end_time": 43}, {"type": "SWITCH_DISHWASHER_S1", "name": "SWITCH_DISHWASHER_S1_55", "start_time": 55, "end_time": 55}, {"type": "SWITCH_DISHWASHER_S1", "name": "SWITCH_DISHWASHER_S1_68", "start_time": 68, "end_time": 68}, {"type": "SWITCH_DISHWASHER_S1", "name": "SWITCH_DISHWASHER_S1_79", "start_time": 79, "end_time": 79}, {"type": "SWITCH_DISHWASHER_S1", "name": "SWITCH_DISHWASHER_S1_87", "start_time": 87, "end_time": 87}, {"type": "SWITCH_DISHWASHER_S1", "name": "SWITCH_DISHWASHER_S1_118", "start_time": 118, "end_time": 118}, {"type": "SWITCH_DISHWASHER_S1", "name": "SWITCH_DISHWASHER_S1_134", "start_time": 134, "end_time": 134}, {"type": "FRIDGE_S2", "name": "FRIDGE_S2_11", "start_time": 11, "end_time": 11}, {"type": "FRIDGE_S2", "name": "FRIDGE_S2_26", "start_time": 26, "end_time": 27}, {"type": "FRIDGE_S2", "name": "FRIDGE_S2_142", "start_time": 142, "end_time": 142}, {"type": "FRIDGE_S2", "name": "FRIDGE_S2_143", "start_time": 143, "end_time": 144}, {"type": "FRIDGE_S1", "name": "FRIDGE_S1_10", "start_time": 10, "end_time": 11}, {"type": "FRIDGE_S1", "name": "FRIDGE_S1_27", "start_time": 27, "end_time": 27}, {"type": "FRIDGE_S1", "name": "FRIDGE_S1_141", "start_time": 141, "end_time": 141}, {"type": "FRIDGE_S1", "name": "FRIDGE_S1_144", "start_time": 144, "end_time": 144}, {"type": "LOWERDRAWER_S2", "name": "LOWERDRAWER_S2_153", "start_time": 153, "end_time": 153}, {"type": "UPPERDRAWER", "name": "UPPERDRAWER_155", "start_time": 155, "end_time": 155}, {"type": "UPPERDRAWER", "name": "UPPERDRAWER_155", "start_time": 155, "end_time": 156}, {"type": "UPPERDRAWER", "name": "UPPERDRAWER_156", "start_time": 156, "end_time": 156}, {"type": "DISHWASHER_S3", "name": "DISHWASHER_S3_58", "start_time": 58, "end_time": 58}, {"type": "LOWERDRAWER_S1", "name": "LOWERDRAWER_S1_152", "start_time": 152, "end_time": 152}, {"type": "LOWERDRAWER_S1", "name": "LOWERDRAWER_S1_154", "start_time": 154, "end_time": 154}, {"type": "DISHWASHER_S2", "name": "DISHWASHER_S2_35", "start_time": 35, "end_time": 36}, {"type": "DISHWASHER_S2", "name": "DISHWASHER_S2_43", "start_time": 43, "end_time": 43}, {"type": "DISHWASHER_S2", "name": "DISHWASHER_S2_55", "start_time": 55, "end_time": 55}, {"type": "DISHWASHER_S2", "name": "DISHWASHER_S2_67", "start_time": 67, "end_time": 68}, {"type": "DISHWASHER_S2", "name": "DISHWASHER_S2_79", "start_time": 79, "end_time": 79}, {"type": "DISHWASHER_S2", "name": "DISHWASHER_S2_87", "start_time": 87, "end_time": 87}, {"type": "DISHWASHER_S2", "name": "DISHWASHER_S2_118", "start_time": 118, "end_time": 118}, {"type": "DISHWASHER_S2", "name": "DISHWASHER_S2_127", "start_time": 127, "end_time": 127}, {"type": "DISHWASHER_S2", "name": "DISHWASHER_S2_127", "start_time": 127, "end_time": 128}, {"type": "DISHWASHER_S2", "name": "DISHWASHER_S2_134", "start_time": 134, "end_time": 134}]}